{
  "parse": [
    {
      "V337493": {
        "id": "V337493",
        "indicator": "SPEECHACT",
        "type": "SA_TELL",
        "word": null,
        "roles": {
          "CONTENT": "#V333508",
          "LEX": "TRIED"
        },
        "start": 0,
        "end": 23
      },
      "V333508": {
        "id": "V333508",
        "indicator": "F",
        "type": "TRY",
        "word": "TRY",
        "roles": {
          "AGENT": "#V337494",
          "FORMAL": "#V333545",
          "TENSE": "PAST",
          "LEX": "TRIED",
          "WNSENSE": "try%1:04:00::"
        },
        "start": 0,
        "end": 23
      },
      "V337494": {
        "id": "V337494",
        "indicator": "IMPRO",
        "type": "REFERENTIAL-SEM",
        "word": null,
        "roles": {
          "PROFORM": "SUBJ"
        },
        "start": 0,
        "end": 23
      },
      "V333545": {
        "id": "V333545",
        "indicator": "F",
        "type": "CAUSE-COVER",
        "word": "COVER",
        "roles": {
          "AGENT": "#V337494",
          "AFFECTED": "#V333604",
          "MANNER": "#V333585",
          "VFORM": "BASE",
          "LEX": "COVER",
          "WNSENSE": "cover%2:35:00::"
        },
        "start": 6,
        "end": 23
      },
      "V333585": {
        "id": "V333585",
        "indicator": "F",
        "type": "COMPLETELY",
        "word": "UP",
        "roles": {
          "FIGURE": "#V333545",
          "LEX": "UP",
          "WNSENSE": "up%4:02:05::"
        },
        "start": 15,
        "end": 18
      },
      "V333604": {
        "id": "V333604",
        "indicator": "PRO",
        "type": "REFERENTIAL-SEM",
        "word": "THAT",
        "roles": {
          "PROFORM": "THAT",
          "LEX": "THAT",
          "WNSENSE": "entity%1:03:00"
        },
        "start": 18,
        "end": 23
      },
      "root": "#V337493"
    },
    {
      "V335405": {
        "id": "V335405",
        "indicator": "SPEECHACT",
        "type": "SA_TELL",
        "word": null,
        "roles": {
          "CONTENT": "#V333633",
          "LEX": "HAPPENED"
        },
        "start": 23,
        "end": 64
      },
      "V333633": {
        "id": "V333633",
        "indicator": "F",
        "type": "HAPPEN",
        "word": "HAPPEN",
        "roles": {
          "NEUTRAL": "#V333612",
          "FORMAL": "#V333666",
          "MOD": "#V333621",
          "TENSE": "PAST",
          "LEX": "HAPPENED",
          "WNSENSE": "happen%2:41:00::"
        },
        "start": 23,
        "end": 64
      },
      "V333612": {
        "id": "V333612",
        "indicator": "PRO",
        "type": "REFERENTIAL-SEM",
        "word": "IT",
        "roles": {
          "PROFORM": "IT",
          "LEX": "IT",
          "WNSENSE": "entity%1:03:00",
          "COREF": "#V333508"
        },
        "start": 23,
        "end": 26
      },
      "V333621": {
        "id": "V333621",
        "indicator": "F",
        "type": "MODIFIER",
        "word": "EVEN",
        "roles": {
          "FIGURE": "#V333633",
          "LEX": "EVEN",
          "WNSENSE": "even%4:02:00::"
        },
        "start": 26,
        "end": 31
      },
      "V333666": {
        "id": "V333666",
        "indicator": "F",
        "type": "RESCUE",
        "word": "SAVE",
        "roles": {
          "AGENT": "#V333612",
          "AFFECTED": "#V333687",
          "VFORM": "BASE",
          "LEX": "SAVE",
          "WNSENSE": "save%2:41:01::"
        },
        "start": 40,
        "end": 64
      },
      "V333687": {
        "id": "V333687",
        "indicator": "THE",
        "type": "INFORMATION-FUNCTION-OBJECT",
        "word": "REPUTATION",
        "roles": {
          "MOD": "#V333680",
          "ASSOC-POSS": "#V333677",
          "LEX": "REPUTATION",
          "WNSENSE": "communication%1:03:00"
        },
        "start": 48,
        "end": 64
      },
      "V333677": {
        "id": "V333677",
        "indicator": "PRO",
        "type": "PERSON",
        "word": "MY",
        "roles": {
          "LEX": "MY",
          "PROFORM": "MY",
          "WNSENSE": "person%1:03:00",
          "COREF": "USER"
        },
        "start": 48,
        "end": 64
      },
      "V333680": {
        "id": "V333680",
        "indicator": "F",
        "type": "OWN",
        "word": "OWN",
        "roles": {
          "FIGURE": "#V333687",
          "LEX": "OWN"
        },
        "start": 51,
        "end": 55
      },
      "root": "#V335405"
    },
    {
      "V337493": {
        "id": "V337493",
        "indicator": "SPEECHACT",
        "type": "SA_TELL",
        "word": null,
        "roles": {
          "CONTENT": "#V333508",
          "LEX": "TRIED"
        },
        "start": 0,
        "end": 23
      },
      "V333508": {
        "id": "V333508",
        "indicator": "F",
        "type": "TRY",
        "word": "TRY",
        "roles": {
          "AGENT": "#V337494",
          "FORMAL": "#V333545",
          "TENSE": "PAST",
          "LEX": "TRIED",
          "WNSENSE": "try%1:04:00::"
        },
        "start": 0,
        "end": 23
      },
      "V337494": {
        "id": "V337494",
        "indicator": "IMPRO",
        "type": "REFERENTIAL-SEM",
        "word": null,
        "roles": {
          "PROFORM": "SUBJ"
        },
        "start": 0,
        "end": 23
      },
      "V333545": {
        "id": "V333545",
        "indicator": "F",
        "type": "CAUSE-COVER",
        "word": "COVER",
        "roles": {
          "AGENT": "#V337494",
          "AFFECTED": "#V333604",
          "MANNER": "#V333585",
          "VFORM": "BASE",
          "LEX": "COVER",
          "WNSENSE": "cover%2:35:00::"
        },
        "start": 6,
        "end": 23
      },
      "V333585": {
        "id": "V333585",
        "indicator": "F",
        "type": "COMPLETELY",
        "word": "UP",
        "roles": {
          "FIGURE": "#V333545",
          "LEX": "UP",
          "WNSENSE": "up%4:02:05::"
        },
        "start": 15,
        "end": 18
      },
      "V333604": {
        "id": "V333604",
        "indicator": "PRO",
        "type": "REFERENTIAL-SEM",
        "word": "THAT",
        "roles": {
          "PROFORM": "THAT",
          "LEX": "THAT",
          "WNSENSE": "entity%1:03:00"
        },
        "start": 18,
        "end": 23
      },
      "root": "#V337493"
    },
    {
      "V335402": {
        "id": "V335402",
        "indicator": "SPEECHACT",
        "type": "SA_TELL",
        "word": null,
        "roles": {
          "CONTENT": "#V333633",
          "LEX": "HAPPENED"
        },
        "start": 23,
        "end": 65
      },
      "V333633": {
        "id": "V333633",
        "indicator": "F",
        "type": "HAPPEN",
        "word": "HAPPEN",
        "roles": {
          "NEUTRAL": "#V333612",
          "FORMAL": "#V333670",
          "MOD": "#V333621",
          "TENSE": "PAST",
          "LEX": "HAPPENED",
          "WNSENSE": "happen%2:41:00::"
        },
        "start": 23,
        "end": 65
      },
      "V333612": {
        "id": "V333612",
        "indicator": "PRO",
        "type": "REFERENTIAL-SEM",
        "word": "IT",
        "roles": {
          "PROFORM": "IT",
          "LEX": "IT",
          "WNSENSE": "entity%1:03:00"
        },
        "start": 23,
        "end": 26
      },
      "V333621": {
        "id": "V333621",
        "indicator": "F",
        "type": "MODIFIER",
        "word": "EVEN",
        "roles": {
          "FIGURE": "#V333633",
          "LEX": "EVEN",
          "WNSENSE": "even%4:02:00::"
        },
        "start": 26,
        "end": 31
      },
      "V333670": {
        "id": "V333670",
        "indicator": "F",
        "type": "RETAIN",
        "word": "SAVE",
        "roles": {
          "AGENT": "#V333612",
          "AFFECTED": "#V333687",
          "VFORM": "BASE",
          "LEX": "SAVE",
          "WNSENSE": "save%2:40:00::"
        },
        "start": 40,
        "end": 65
      },
      "V333687": {
        "id": "V333687",
        "indicator": "THE",
        "type": "INFORMATION-FUNCTION-OBJECT",
        "word": "REPUTATION",
        "roles": {
          "MOD": "#V333680",
          "ASSOC-POSS": "#V333677",
          "LEX": "REPUTATION",
          "WNSENSE": "communication%1:03:00"
        },
        "start": 48,
        "end": 65
      },
      "V333677": {
        "id": "V333677",
        "indicator": "PRO",
        "type": "PERSON",
        "word": "MY",
        "roles": {
          "LEX": "MY",
          "PROFORM": "MY",
          "WNSENSE": "person%1:03:00"
        },
        "start": 48,
        "end": 65
      },
      "V333680": {
        "id": "V333680",
        "indicator": "F",
        "type": "OWN",
        "word": "OWN",
        "roles": {
          "FIGURE": "#V333687",
          "LEX": "OWN"
        },
        "start": 51,
        "end": 55
      },
      "root": "#V335402"
    },
    {
      "V337490": {
        "id": "V337490",
        "indicator": "SPEECHACT",
        "type": "SA_TELL",
        "word": null,
        "roles": {
          "CONTENT": "#V333508",
          "LEX": "TRIED"
        },
        "start": 0,
        "end": 23
      },
      "V333508": {
        "id": "V333508",
        "indicator": "F",
        "type": "TRY",
        "word": "TRY",
        "roles": {
          "AGENT": "#V337491",
          "FORMAL": "#V333547",
          "TENSE": "PAST",
          "LEX": "TRIED",
          "WNSENSE": "try%1:04:00::"
        },
        "start": 0,
        "end": 23
      },
      "V337491": {
        "id": "V337491",
        "indicator": "IMPRO",
        "type": "REFERENTIAL-SEM",
        "word": null,
        "roles": {
          "PROFORM": "SUBJ"
        },
        "start": 0,
        "end": 23
      },
      "V333547": {
        "id": "V333547",
        "indicator": "F",
        "type": "TAKING-CARE-OF",
        "word": "COVER",
        "roles": {
          "AGENT": "#V337491",
          "AFFECTED": "#V333604",
          "MANNER": "#V333585",
          "VFORM": "BASE",
          "LEX": "COVER",
          "WNSENSE": "handle%2:41:00"
        },
        "start": 6,
        "end": 23
      },
      "V333585": {
        "id": "V333585",
        "indicator": "F",
        "type": "COMPLETELY",
        "word": "UP",
        "roles": {
          "FIGURE": "#V333547",
          "LEX": "UP",
          "WNSENSE": "up%4:02:05::"
        },
        "start": 15,
        "end": 18
      },
      "V333604": {
        "id": "V333604",
        "indicator": "PRO",
        "type": "REFERENTIAL-SEM",
        "word": "THAT",
        "roles": {
          "PROFORM": "THAT",
          "LEX": "THAT",
          "WNSENSE": "entity%1:03:00"
        },
        "start": 18,
        "end": 23
      },
      "root": "#V337490"
    },
    {
      "V335405": {
        "id": "V335405",
        "indicator": "SPEECHACT",
        "type": "SA_TELL",
        "word": null,
        "roles": {
          "CONTENT": "#V333633",
          "LEX": "HAPPENED"
        },
        "start": 23,
        "end": 65
      },
      "V333633": {
        "id": "V333633",
        "indicator": "F",
        "type": "HAPPEN",
        "word": "HAPPEN",
        "roles": {
          "NEUTRAL": "#V333612",
          "FORMAL": "#V333666",
          "MOD": "#V333621",
          "TENSE": "PAST",
          "LEX": "HAPPENED",
          "WNSENSE": "happen%2:41:00::"
        },
        "start": 23,
        "end": 65
      },
      "V333612": {
        "id": "V333612",
        "indicator": "PRO",
        "type": "REFERENTIAL-SEM",
        "word": "IT",
        "roles": {
          "PROFORM": "IT",
          "LEX": "IT",
          "WNSENSE": "entity%1:03:00"
        },
        "start": 23,
        "end": 26
      },
      "V333621": {
        "id": "V333621",
        "indicator": "F",
        "type": "MODIFIER",
        "word": "EVEN",
        "roles": {
          "FIGURE": "#V333633",
          "LEX": "EVEN",
          "WNSENSE": "even%4:02:00::"
        },
        "start": 26,
        "end": 31
      },
      "V333666": {
        "id": "V333666",
        "indicator": "F",
        "type": "RESCUE",
        "word": "SAVE",
        "roles": {
          "AGENT": "#V333612",
          "AFFECTED": "#V333687",
          "VFORM": "BASE",
          "LEX": "SAVE",
          "WNSENSE": "save%2:41:01::"
        },
        "start": 40,
        "end": 65
      },
      "V333687": {
        "id": "V333687",
        "indicator": "THE",
        "type": "INFORMATION-FUNCTION-OBJECT",
        "word": "REPUTATION",
        "roles": {
          "MOD": "#V333680",
          "ASSOC-POSS": "#V333677",
          "LEX": "REPUTATION",
          "WNSENSE": "communication%1:03:00"
        },
        "start": 48,
        "end": 65
      },
      "V333677": {
        "id": "V333677",
        "indicator": "PRO",
        "type": "PERSON",
        "word": "MY",
        "roles": {
          "LEX": "MY",
          "PROFORM": "MY",
          "WNSENSE": "person%1:03:00"
        },
        "start": 48,
        "end": 65
      },
      "V333680": {
        "id": "V333680",
        "indicator": "F",
        "type": "OWN",
        "word": "OWN",
        "roles": {
          "FIGURE": "#V333687",
          "LEX": "OWN"
        },
        "start": 51,
        "end": 55
      },
      "root": "#V335405"
    },
    {
      "V337490": {
        "id": "V337490",
        "indicator": "SPEECHACT",
        "type": "SA_TELL",
        "word": null,
        "roles": {
          "CONTENT": "#V333508",
          "LEX": "TRIED"
        },
        "start": 0,
        "end": 23
      },
      "V333508": {
        "id": "V333508",
        "indicator": "F",
        "type": "TRY",
        "word": "TRY",
        "roles": {
          "AGENT": "#V337491",
          "FORMAL": "#V333547",
          "TENSE": "PAST",
          "LEX": "TRIED",
          "WNSENSE": "try%1:04:00::"
        },
        "start": 0,
        "end": 23
      },
      "V337491": {
        "id": "V337491",
        "indicator": "IMPRO",
        "type": "REFERENTIAL-SEM",
        "word": null,
        "roles": {
          "PROFORM": "SUBJ"
        },
        "start": 0,
        "end": 23
      },
      "V333547": {
        "id": "V333547",
        "indicator": "F",
        "type": "TAKING-CARE-OF",
        "word": "COVER",
        "roles": {
          "AGENT": "#V337491",
          "AFFECTED": "#V333604",
          "MANNER": "#V333585",
          "VFORM": "BASE",
          "LEX": "COVER",
          "WNSENSE": "handle%2:41:00"
        },
        "start": 6,
        "end": 23
      },
      "V333585": {
        "id": "V333585",
        "indicator": "F",
        "type": "COMPLETELY",
        "word": "UP",
        "roles": {
          "FIGURE": "#V333547",
          "LEX": "UP",
          "WNSENSE": "up%4:02:05::"
        },
        "start": 15,
        "end": 18
      },
      "V333604": {
        "id": "V333604",
        "indicator": "PRO",
        "type": "REFERENTIAL-SEM",
        "word": "THAT",
        "roles": {
          "PROFORM": "THAT",
          "LEX": "THAT",
          "WNSENSE": "entity%1:03:00"
        },
        "start": 18,
        "end": 23
      },
      "root": "#V337490"
    },
    {
      "V335402": {
        "id": "V335402",
        "indicator": "SPEECHACT",
        "type": "SA_TELL",
        "word": null,
        "roles": {
          "CONTENT": "#V333633",
          "LEX": "HAPPENED"
        },
        "start": 23,
        "end": 65
      },
      "V333633": {
        "id": "V333633",
        "indicator": "F",
        "type": "HAPPEN",
        "word": "HAPPEN",
        "roles": {
          "NEUTRAL": "#V333612",
          "FORMAL": "#V333670",
          "MOD": "#V333621",
          "TENSE": "PAST",
          "LEX": "HAPPENED",
          "WNSENSE": "happen%2:41:00::"
        },
        "start": 23,
        "end": 65
      },
      "V333612": {
        "id": "V333612",
        "indicator": "PRO",
        "type": "REFERENTIAL-SEM",
        "word": "IT",
        "roles": {
          "PROFORM": "IT",
          "LEX": "IT",
          "WNSENSE": "entity%1:03:00"
        },
        "start": 23,
        "end": 26
      },
      "V333621": {
        "id": "V333621",
        "indicator": "F",
        "type": "MODIFIER",
        "word": "EVEN",
        "roles": {
          "FIGURE": "#V333633",
          "LEX": "EVEN",
          "WNSENSE": "even%4:02:00::"
        },
        "start": 26,
        "end": 31
      },
      "V333670": {
        "id": "V333670",
        "indicator": "F",
        "type": "RETAIN",
        "word": "SAVE",
        "roles": {
          "AGENT": "#V333612",
          "AFFECTED": "#V333687",
          "VFORM": "BASE",
          "LEX": "SAVE",
          "WNSENSE": "save%2:40:00::"
        },
        "start": 40,
        "end": 65
      },
      "V333687": {
        "id": "V333687",
        "indicator": "THE",
        "type": "INFORMATION-FUNCTION-OBJECT",
        "word": "REPUTATION",
        "roles": {
          "MOD": "#V333680",
          "ASSOC-POSS": "#V333677",
          "LEX": "REPUTATION",
          "WNSENSE": "communication%1:03:00"
        },
        "start": 48,
        "end": 65
      },
      "V333677": {
        "id": "V333677",
        "indicator": "PRO",
        "type": "PERSON",
        "word": "MY",
        "roles": {
          "LEX": "MY",
          "PROFORM": "MY",
          "WNSENSE": "person%1:03:00"
        },
        "start": 48,
        "end": 65
      },
      "V333680": {
        "id": "V333680",
        "indicator": "F",
        "type": "OWN",
        "word": "OWN",
        "roles": {
          "FIGURE": "#V333687",
          "LEX": "OWN"
        },
        "start": 51,
        "end": 55
      },
      "root": "#V335402"
    },
    {
      "V337487": {
        "id": "V337487",
        "indicator": "SPEECHACT",
        "type": "SA_TELL",
        "word": null,
        "roles": {
          "CONTENT": "#V333508",
          "LEX": "TRIED"
        },
        "start": 0,
        "end": 23
      },
      "V333508": {
        "id": "V333508",
        "indicator": "F",
        "type": "TRY",
        "word": "TRY",
        "roles": {
          "AGENT": "#V337488",
          "FORMAL": "#V333545",
          "TENSE": "PAST",
          "LEX": "TRIED",
          "WNSENSE": "try%1:04:00::"
        },
        "start": 0,
        "end": 23
      },
      "V337488": {
        "id": "V337488",
        "indicator": "IMPRO",
        "type": "REFERENTIAL-SEM",
        "word": null,
        "roles": {
          "PROFORM": "SUBJ"
        },
        "start": 0,
        "end": 23
      },
      "V333545": {
        "id": "V333545",
        "indicator": "F",
        "type": "CAUSE-COVER",
        "word": "COVER",
        "roles": {
          "AGENT": "#V337488",
          "AFFECTED": "#V333604",
          "RESULT": "#V333584",
          "VFORM": "BASE",
          "LEX": "COVER",
          "WNSENSE": "cover%2:35:00::"
        },
        "start": 6,
        "end": 23
      },
      "V333584": {
        "id": "V333584",
        "indicator": "F",
        "type": "DIRECTION-UP",
        "word": "UP",
        "roles": {
          "FIGURE": "#V333604",
          "LEX": "UP"
        },
        "start": 15,
        "end": 18
      },
      "V333604": {
        "id": "V333604",
        "indicator": "PRO",
        "type": "REFERENTIAL-SEM",
        "word": "THAT",
        "roles": {
          "PROFORM": "THAT",
          "LEX": "THAT",
          "WNSENSE": "entity%1:03:00"
        },
        "start": 18,
        "end": 23
      },
      "root": "#V337487"
    },
    {
      "V335405": {
        "id": "V335405",
        "indicator": "SPEECHACT",
        "type": "SA_TELL",
        "word": null,
        "roles": {
          "CONTENT": "#V333633",
          "LEX": "HAPPENED"
        },
        "start": 23,
        "end": 65
      },
      "V333633": {
        "id": "V333633",
        "indicator": "F",
        "type": "HAPPEN",
        "word": "HAPPEN",
        "roles": {
          "NEUTRAL": "#V333612",
          "FORMAL": "#V333666",
          "MOD": "#V333621",
          "TENSE": "PAST",
          "LEX": "HAPPENED",
          "WNSENSE": "happen%2:41:00::"
        },
        "start": 23,
        "end": 65
      },
      "V333612": {
        "id": "V333612",
        "indicator": "PRO",
        "type": "REFERENTIAL-SEM",
        "word": "IT",
        "roles": {
          "PROFORM": "IT",
          "LEX": "IT",
          "WNSENSE": "entity%1:03:00"
        },
        "start": 23,
        "end": 26
      },
      "V333621": {
        "id": "V333621",
        "indicator": "F",
        "type": "MODIFIER",
        "word": "EVEN",
        "roles": {
          "FIGURE": "#V333633",
          "LEX": "EVEN",
          "WNSENSE": "even%4:02:00::"
        },
        "start": 26,
        "end": 31
      },
      "V333666": {
        "id": "V333666",
        "indicator": "F",
        "type": "RESCUE",
        "word": "SAVE",
        "roles": {
          "AGENT": "#V333612",
          "AFFECTED": "#V333687",
          "VFORM": "BASE",
          "LEX": "SAVE",
          "WNSENSE": "save%2:41:01::"
        },
        "start": 40,
        "end": 65
      },
      "V333687": {
        "id": "V333687",
        "indicator": "THE",
        "type": "INFORMATION-FUNCTION-OBJECT",
        "word": "REPUTATION",
        "roles": {
          "MOD": "#V333680",
          "ASSOC-POSS": "#V333677",
          "LEX": "REPUTATION",
          "WNSENSE": "communication%1:03:00"
        },
        "start": 48,
        "end": 65
      },
      "V333677": {
        "id": "V333677",
        "indicator": "PRO",
        "type": "PERSON",
        "word": "MY",
        "roles": {
          "LEX": "MY",
          "PROFORM": "MY",
          "WNSENSE": "person%1:03:00"
        },
        "start": 48,
        "end": 65
      },
      "V333680": {
        "id": "V333680",
        "indicator": "F",
        "type": "OWN",
        "word": "OWN",
        "roles": {
          "FIGURE": "#V333687",
          "LEX": "OWN"
        },
        "start": 51,
        "end": 55
      },
      "root": "#V335405"
    },
    {
      "V337487": {
        "id": "V337487",
        "indicator": "SPEECHACT",
        "type": "SA_TELL",
        "word": null,
        "roles": {
          "CONTENT": "#V333508",
          "LEX": "TRIED"
        },
        "start": 0,
        "end": 23
      },
      "V333508": {
        "id": "V333508",
        "indicator": "F",
        "type": "TRY",
        "word": "TRY",
        "roles": {
          "AGENT": "#V337488",
          "FORMAL": "#V333545",
          "TENSE": "PAST",
          "LEX": "TRIED",
          "WNSENSE": "try%1:04:00::"
        },
        "start": 0,
        "end": 23
      },
      "V337488": {
        "id": "V337488",
        "indicator": "IMPRO",
        "type": "REFERENTIAL-SEM",
        "word": null,
        "roles": {
          "PROFORM": "SUBJ"
        },
        "start": 0,
        "end": 23
      },
      "V333545": {
        "id": "V333545",
        "indicator": "F",
        "type": "CAUSE-COVER",
        "word": "COVER",
        "roles": {
          "AGENT": "#V337488",
          "AFFECTED": "#V333604",
          "RESULT": "#V333584",
          "VFORM": "BASE",
          "LEX": "COVER",
          "WNSENSE": "cover%2:35:00::"
        },
        "start": 6,
        "end": 23
      },
      "V333584": {
        "id": "V333584",
        "indicator": "F",
        "type": "DIRECTION-UP",
        "word": "UP",
        "roles": {
          "FIGURE": "#V333604",
          "LEX": "UP"
        },
        "start": 15,
        "end": 18
      },
      "V333604": {
        "id": "V333604",
        "indicator": "PRO",
        "type": "REFERENTIAL-SEM",
        "word": "THAT",
        "roles": {
          "PROFORM": "THAT",
          "LEX": "THAT",
          "WNSENSE": "entity%1:03:00"
        },
        "start": 18,
        "end": 23
      },
      "root": "#V337487"
    },
    {
      "V335402": {
        "id": "V335402",
        "indicator": "SPEECHACT",
        "type": "SA_TELL",
        "word": null,
        "roles": {
          "CONTENT": "#V333633",
          "LEX": "HAPPENED"
        },
        "start": 23,
        "end": 65
      },
      "V333633": {
        "id": "V333633",
        "indicator": "F",
        "type": "HAPPEN",
        "word": "HAPPEN",
        "roles": {
          "NEUTRAL": "#V333612",
          "FORMAL": "#V333670",
          "MOD": "#V333621",
          "TENSE": "PAST",
          "LEX": "HAPPENED",
          "WNSENSE": "happen%2:41:00::"
        },
        "start": 23,
        "end": 65
      },
      "V333612": {
        "id": "V333612",
        "indicator": "PRO",
        "type": "REFERENTIAL-SEM",
        "word": "IT",
        "roles": {
          "PROFORM": "IT",
          "LEX": "IT",
          "WNSENSE": "entity%1:03:00"
        },
        "start": 23,
        "end": 26
      },
      "V333621": {
        "id": "V333621",
        "indicator": "F",
        "type": "MODIFIER",
        "word": "EVEN",
        "roles": {
          "FIGURE": "#V333633",
          "LEX": "EVEN",
          "WNSENSE": "even%4:02:00::"
        },
        "start": 26,
        "end": 31
      },
      "V333670": {
        "id": "V333670",
        "indicator": "F",
        "type": "RETAIN",
        "word": "SAVE",
        "roles": {
          "AGENT": "#V333612",
          "AFFECTED": "#V333687",
          "VFORM": "BASE",
          "LEX": "SAVE",
          "WNSENSE": "save%2:40:00::"
        },
        "start": 40,
        "end": 65
      },
      "V333687": {
        "id": "V333687",
        "indicator": "THE",
        "type": "INFORMATION-FUNCTION-OBJECT",
        "word": "REPUTATION",
        "roles": {
          "MOD": "#V333680",
          "ASSOC-POSS": "#V333677",
          "LEX": "REPUTATION",
          "WNSENSE": "communication%1:03:00"
        },
        "start": 48,
        "end": 65
      },
      "V333677": {
        "id": "V333677",
        "indicator": "PRO",
        "type": "PERSON",
        "word": "MY",
        "roles": {
          "LEX": "MY",
          "PROFORM": "MY",
          "WNSENSE": "person%1:03:00"
        },
        "start": 48,
        "end": 65
      },
      "V333680": {
        "id": "V333680",
        "indicator": "F",
        "type": "OWN",
        "word": "OWN",
        "roles": {
          "FIGURE": "#V333687",
          "LEX": "OWN"
        },
        "start": 51,
        "end": 55
      },
      "root": "#V335402"
    },
    {
      "V337484": {
        "id": "V337484",
        "indicator": "SPEECHACT",
        "type": "SA_TELL",
        "word": null,
        "roles": {
          "CONTENT": "#V333508",
          "LEX": "TRIED"
        },
        "start": 0,
        "end": 23
      },
      "V333508": {
        "id": "V333508",
        "indicator": "F",
        "type": "TRY",
        "word": "TRY",
        "roles": {
          "AGENT": "#V337485",
          "FORMAL": "#V333547",
          "TENSE": "PAST",
          "LEX": "TRIED",
          "WNSENSE": "try%1:04:00::"
        },
        "start": 0,
        "end": 23
      },
      "V337485": {
        "id": "V337485",
        "indicator": "IMPRO",
        "type": "REFERENTIAL-SEM",
        "word": null,
        "roles": {
          "PROFORM": "SUBJ"
        },
        "start": 0,
        "end": 23
      },
      "V333547": {
        "id": "V333547",
        "indicator": "F",
        "type": "TAKING-CARE-OF",
        "word": "COVER",
        "roles": {
          "AGENT": "#V337485",
          "AFFECTED": "#V333604",
          "RESULT": "#V333584",
          "VFORM": "BASE",
          "LEX": "COVER",
          "WNSENSE": "handle%2:41:00"
        },
        "start": 6,
        "end": 23
      },
      "V333584": {
        "id": "V333584",
        "indicator": "F",
        "type": "DIRECTION-UP",
        "word": "UP",
        "roles": {
          "FIGURE": "#V333604",
          "LEX": "UP"
        },
        "start": 15,
        "end": 18
      },
      "V333604": {
        "id": "V333604",
        "indicator": "PRO",
        "type": "REFERENTIAL-SEM",
        "word": "THAT",
        "roles": {
          "PROFORM": "THAT",
          "LEX": "THAT",
          "WNSENSE": "entity%1:03:00"
        },
        "start": 18,
        "end": 23
      },
      "root": "#V337484"
    },
    {
      "V335405": {
        "id": "V335405",
        "indicator": "SPEECHACT",
        "type": "SA_TELL",
        "word": null,
        "roles": {
          "CONTENT": "#V333633",
          "LEX": "HAPPENED"
        },
        "start": 23,
        "end": 65
      },
      "V333633": {
        "id": "V333633",
        "indicator": "F",
        "type": "HAPPEN",
        "word": "HAPPEN",
        "roles": {
          "NEUTRAL": "#V333612",
          "FORMAL": "#V333666",
          "MOD": "#V333621",
          "TENSE": "PAST",
          "LEX": "HAPPENED",
          "WNSENSE": "happen%2:41:00::"
        },
        "start": 23,
        "end": 65
      },
      "V333612": {
        "id": "V333612",
        "indicator": "PRO",
        "type": "REFERENTIAL-SEM",
        "word": "IT",
        "roles": {
          "PROFORM": "IT",
          "LEX": "IT",
          "WNSENSE": "entity%1:03:00"
        },
        "start": 23,
        "end": 26
      },
      "V333621": {
        "id": "V333621",
        "indicator": "F",
        "type": "MODIFIER",
        "word": "EVEN",
        "roles": {
          "FIGURE": "#V333633",
          "LEX": "EVEN",
          "WNSENSE": "even%4:02:00::"
        },
        "start": 26,
        "end": 31
      },
      "V333666": {
        "id": "V333666",
        "indicator": "F",
        "type": "RESCUE",
        "word": "SAVE",
        "roles": {
          "AGENT": "#V333612",
          "AFFECTED": "#V333687",
          "VFORM": "BASE",
          "LEX": "SAVE",
          "WNSENSE": "save%2:41:01::"
        },
        "start": 40,
        "end": 65
      },
      "V333687": {
        "id": "V333687",
        "indicator": "THE",
        "type": "INFORMATION-FUNCTION-OBJECT",
        "word": "REPUTATION",
        "roles": {
          "MOD": "#V333680",
          "ASSOC-POSS": "#V333677",
          "LEX": "REPUTATION",
          "WNSENSE": "communication%1:03:00"
        },
        "start": 48,
        "end": 65
      },
      "V333677": {
        "id": "V333677",
        "indicator": "PRO",
        "type": "PERSON",
        "word": "MY",
        "roles": {
          "LEX": "MY",
          "PROFORM": "MY",
          "WNSENSE": "person%1:03:00"
        },
        "start": 48,
        "end": 65
      },
      "V333680": {
        "id": "V333680",
        "indicator": "F",
        "type": "OWN",
        "word": "OWN",
        "roles": {
          "FIGURE": "#V333687",
          "LEX": "OWN"
        },
        "start": 51,
        "end": 55
      },
      "root": "#V335405"
    },
    {
      "V337484": {
        "id": "V337484",
        "indicator": "SPEECHACT",
        "type": "SA_TELL",
        "word": null,
        "roles": {
          "CONTENT": "#V333508",
          "LEX": "TRIED"
        },
        "start": 0,
        "end": 23
      },
      "V333508": {
        "id": "V333508",
        "indicator": "F",
        "type": "TRY",
        "word": "TRY",
        "roles": {
          "AGENT": "#V337485",
          "FORMAL": "#V333547",
          "TENSE": "PAST",
          "LEX": "TRIED",
          "WNSENSE": "try%1:04:00::"
        },
        "start": 0,
        "end": 23
      },
      "V337485": {
        "id": "V337485",
        "indicator": "IMPRO",
        "type": "REFERENTIAL-SEM",
        "word": null,
        "roles": {
          "PROFORM": "SUBJ"
        },
        "start": 0,
        "end": 23
      },
      "V333547": {
        "id": "V333547",
        "indicator": "F",
        "type": "TAKING-CARE-OF",
        "word": "COVER",
        "roles": {
          "AGENT": "#V337485",
          "AFFECTED": "#V333604",
          "RESULT": "#V333584",
          "VFORM": "BASE",
          "LEX": "COVER",
          "WNSENSE": "handle%2:41:00"
        },
        "start": 6,
        "end": 23
      },
      "V333584": {
        "id": "V333584",
        "indicator": "F",
        "type": "DIRECTION-UP",
        "word": "UP",
        "roles": {
          "FIGURE": "#V333604",
          "LEX": "UP"
        },
        "start": 15,
        "end": 18
      },
      "V333604": {
        "id": "V333604",
        "indicator": "PRO",
        "type": "REFERENTIAL-SEM",
        "word": "THAT",
        "roles": {
          "PROFORM": "THAT",
          "LEX": "THAT",
          "WNSENSE": "entity%1:03:00"
        },
        "start": 18,
        "end": 23
      },
      "root": "#V337484"
    },
    {
      "V335402": {
        "id": "V335402",
        "indicator": "SPEECHACT",
        "type": "SA_TELL",
        "word": null,
        "roles": {
          "CONTENT": "#V333633",
          "LEX": "HAPPENED"
        },
        "start": 23,
        "end": 65
      },
      "V333633": {
        "id": "V333633",
        "indicator": "F",
        "type": "HAPPEN",
        "word": "HAPPEN",
        "roles": {
          "NEUTRAL": "#V333612",
          "FORMAL": "#V333670",
          "MOD": "#V333621",
          "TENSE": "PAST",
          "LEX": "HAPPENED",
          "WNSENSE": "happen%2:41:00::"
        },
        "start": 23,
        "end": 65
      },
      "V333612": {
        "id": "V333612",
        "indicator": "PRO",
        "type": "REFERENTIAL-SEM",
        "word": "IT",
        "roles": {
          "PROFORM": "IT",
          "LEX": "IT",
          "WNSENSE": "entity%1:03:00"
        },
        "start": 23,
        "end": 26
      },
      "V333621": {
        "id": "V333621",
        "indicator": "F",
        "type": "MODIFIER",
        "word": "EVEN",
        "roles": {
          "FIGURE": "#V333633",
          "LEX": "EVEN",
          "WNSENSE": "even%4:02:00::"
        },
        "start": 26,
        "end": 31
      },
      "V333670": {
        "id": "V333670",
        "indicator": "F",
        "type": "RETAIN",
        "word": "SAVE",
        "roles": {
          "AGENT": "#V333612",
          "AFFECTED": "#V333687",
          "VFORM": "BASE",
          "LEX": "SAVE",
          "WNSENSE": "save%2:40:00::"
        },
        "start": 40,
        "end": 65
      },
      "V333687": {
        "id": "V333687",
        "indicator": "THE",
        "type": "INFORMATION-FUNCTION-OBJECT",
        "word": "REPUTATION",
        "roles": {
          "MOD": "#V333680",
          "ASSOC-POSS": "#V333677",
          "LEX": "REPUTATION",
          "WNSENSE": "communication%1:03:00"
        },
        "start": 48,
        "end": 65
      },
      "V333677": {
        "id": "V333677",
        "indicator": "PRO",
        "type": "PERSON",
        "word": "MY",
        "roles": {
          "LEX": "MY",
          "PROFORM": "MY",
          "WNSENSE": "person%1:03:00"
        },
        "start": 48,
        "end": 65
      },
      "V333680": {
        "id": "V333680",
        "indicator": "F",
        "type": "OWN",
        "word": "OWN",
        "roles": {
          "FIGURE": "#V333687",
          "LEX": "OWN"
        },
        "start": 51,
        "end": 55
      },
      "root": "#V335402"
    },
    {
      "V337493": {
        "id": "V337493",
        "indicator": "SPEECHACT",
        "type": "SA_TELL",
        "word": null,
        "roles": {
          "CONTENT": "#V333508",
          "LEX": "TRIED"
        },
        "start": 0,
        "end": 23
      },
      "V333508": {
        "id": "V333508",
        "indicator": "F",
        "type": "TRY",
        "word": "TRY",
        "roles": {
          "AGENT": "#V337494",
          "FORMAL": "#V333545",
          "TENSE": "PAST",
          "LEX": "TRIED",
          "WNSENSE": "try%1:04:00::"
        },
        "start": 0,
        "end": 23
      },
      "V337494": {
        "id": "V337494",
        "indicator": "IMPRO",
        "type": "REFERENTIAL-SEM",
        "word": null,
        "roles": {
          "PROFORM": "SUBJ"
        },
        "start": 0,
        "end": 23
      },
      "V333545": {
        "id": "V333545",
        "indicator": "F",
        "type": "CAUSE-COVER",
        "word": "COVER",
        "roles": {
          "AGENT": "#V337494",
          "AFFECTED": "#V333604",
          "MANNER": "#V333585",
          "VFORM": "BASE",
          "LEX": "COVER",
          "WNSENSE": "cover%2:35:00::"
        },
        "start": 6,
        "end": 23
      },
      "V333585": {
        "id": "V333585",
        "indicator": "F",
        "type": "COMPLETELY",
        "word": "UP",
        "roles": {
          "FIGURE": "#V333545",
          "LEX": "UP",
          "WNSENSE": "up%4:02:05::"
        },
        "start": 15,
        "end": 18
      },
      "V333604": {
        "id": "V333604",
        "indicator": "PRO",
        "type": "REFERENTIAL-SEM",
        "word": "THAT",
        "roles": {
          "PROFORM": "THAT",
          "LEX": "THAT",
          "WNSENSE": "entity%1:03:00"
        },
        "start": 18,
        "end": 23
      },
      "root": "#V337493"
    },
    {
      "V335479": {
        "id": "V335479",
        "indicator": "SPEECHACT",
        "type": "SA_TELL",
        "word": null,
        "roles": {
          "CONTENT": "#V333633",
          "LEX": "HAPPENED"
        },
        "start": 23,
        "end": 65
      },
      "V333633": {
        "id": "V333633",
        "indicator": "F",
        "type": "HAPPEN",
        "word": "HAPPEN",
        "roles": {
          "NEUTRAL": "#V333788",
          "FORMAL": "#V333666",
          "MOD": "#V333621",
          "TENSE": "PAST",
          "LEX": "HAPPENED",
          "WNSENSE": "happen%2:41:00::"
        },
        "start": 23,
        "end": 65
      },
      "V333788": {
        "id": "V333788",
        "indicator": "THE",
        "type": "QUANTITY-ABSTR",
        "word": null,
        "roles": {
          "FIGURE": "#V333612"
        },
        "start": 23,
        "end": 26
      },
      "V333612": {
        "id": "V333612",
        "indicator": "PRO",
        "type": "REFERENTIAL-SEM",
        "word": "IT",
        "roles": {
          "PROFORM": "IT",
          "LEX": "IT",
          "WNSENSE": "entity%1:03:00"
        },
        "start": 23,
        "end": 26
      },
      "V333621": {
        "id": "V333621",
        "indicator": "F",
        "type": "MODIFIER",
        "word": "EVEN",
        "roles": {
          "FIGURE": "#V333633",
          "LEX": "EVEN",
          "WNSENSE": "even%4:02:00::"
        },
        "start": 26,
        "end": 31
      },
      "V333666": {
        "id": "V333666",
        "indicator": "F",
        "type": "RESCUE",
        "word": "SAVE",
        "roles": {
          "AGENT": "#V333788",
          "AFFECTED": "#V333687",
          "VFORM": "BASE",
          "LEX": "SAVE",
          "WNSENSE": "save%2:41:01::"
        },
        "start": 40,
        "end": 65
      },
      "V333687": {
        "id": "V333687",
        "indicator": "THE",
        "type": "INFORMATION-FUNCTION-OBJECT",
        "word": "REPUTATION",
        "roles": {
          "MOD": "#V333680",
          "ASSOC-POSS": "#V333677",
          "LEX": "REPUTATION",
          "WNSENSE": "communication%1:03:00"
        },
        "start": 48,
        "end": 65
      },
      "V333677": {
        "id": "V333677",
        "indicator": "PRO",
        "type": "PERSON",
        "word": "MY",
        "roles": {
          "LEX": "MY",
          "PROFORM": "MY",
          "WNSENSE": "person%1:03:00"
        },
        "start": 48,
        "end": 65
      },
      "V333680": {
        "id": "V333680",
        "indicator": "F",
        "type": "OWN",
        "word": "OWN",
        "roles": {
          "FIGURE": "#V333687",
          "LEX": "OWN"
        },
        "start": 51,
        "end": 55
      },
      "root": "#V335479"
    },
    {
      "V337490": {
        "id": "V337490",
        "indicator": "SPEECHACT",
        "type": "SA_TELL",
        "word": null,
        "roles": {
          "CONTENT": "#V333508",
          "LEX": "TRIED"
        },
        "start": 0,
        "end": 23
      },
      "V333508": {
        "id": "V333508",
        "indicator": "F",
        "type": "TRY",
        "word": "TRY",
        "roles": {
          "AGENT": "#V337491",
          "FORMAL": "#V333547",
          "TENSE": "PAST",
          "LEX": "TRIED",
          "WNSENSE": "try%1:04:00::"
        },
        "start": 0,
        "end": 23
      },
      "V337491": {
        "id": "V337491",
        "indicator": "IMPRO",
        "type": "REFERENTIAL-SEM",
        "word": null,
        "roles": {
          "PROFORM": "SUBJ"
        },
        "start": 0,
        "end": 23
      },
      "V333547": {
        "id": "V333547",
        "indicator": "F",
        "type": "TAKING-CARE-OF",
        "word": "COVER",
        "roles": {
          "AGENT": "#V337491",
          "AFFECTED": "#V333604",
          "MANNER": "#V333585",
          "VFORM": "BASE",
          "LEX": "COVER",
          "WNSENSE": "handle%2:41:00"
        },
        "start": 6,
        "end": 23
      },
      "V333585": {
        "id": "V333585",
        "indicator": "F",
        "type": "COMPLETELY",
        "word": "UP",
        "roles": {
          "FIGURE": "#V333547",
          "LEX": "UP",
          "WNSENSE": "up%4:02:05::"
        },
        "start": 15,
        "end": 18
      },
      "V333604": {
        "id": "V333604",
        "indicator": "PRO",
        "type": "REFERENTIAL-SEM",
        "word": "THAT",
        "roles": {
          "PROFORM": "THAT",
          "LEX": "THAT",
          "WNSENSE": "entity%1:03:00"
        },
        "start": 18,
        "end": 23
      },
      "root": "#V337490"
    },
    {
      "V335479": {
        "id": "V335479",
        "indicator": "SPEECHACT",
        "type": "SA_TELL",
        "word": null,
        "roles": {
          "CONTENT": "#V333633",
          "LEX": "HAPPENED"
        },
        "start": 23,
        "end": 65
      },
      "V333633": {
        "id": "V333633",
        "indicator": "F",
        "type": "HAPPEN",
        "word": "HAPPEN",
        "roles": {
          "NEUTRAL": "#V333788",
          "FORMAL": "#V333666",
          "MOD": "#V333621",
          "TENSE": "PAST",
          "LEX": "HAPPENED",
          "WNSENSE": "happen%2:41:00::"
        },
        "start": 23,
        "end": 65
      },
      "V333788": {
        "id": "V333788",
        "indicator": "THE",
        "type": "QUANTITY-ABSTR",
        "word": null,
        "roles": {
          "FIGURE": "#V333612"
        },
        "start": 23,
        "end": 26
      },
      "V333612": {
        "id": "V333612",
        "indicator": "PRO",
        "type": "REFERENTIAL-SEM",
        "word": "IT",
        "roles": {
          "PROFORM": "IT",
          "LEX": "IT",
          "WNSENSE": "entity%1:03:00"
        },
        "start": 23,
        "end": 26
      },
      "V333621": {
        "id": "V333621",
        "indicator": "F",
        "type": "MODIFIER",
        "word": "EVEN",
        "roles": {
          "FIGURE": "#V333633",
          "LEX": "EVEN",
          "WNSENSE": "even%4:02:00::"
        },
        "start": 26,
        "end": 31
      },
      "V333666": {
        "id": "V333666",
        "indicator": "F",
        "type": "RESCUE",
        "word": "SAVE",
        "roles": {
          "AGENT": "#V333788",
          "AFFECTED": "#V333687",
          "VFORM": "BASE",
          "LEX": "SAVE",
          "WNSENSE": "save%2:41:01::"
        },
        "start": 40,
        "end": 65
      },
      "V333687": {
        "id": "V333687",
        "indicator": "THE",
        "type": "INFORMATION-FUNCTION-OBJECT",
        "word": "REPUTATION",
        "roles": {
          "MOD": "#V333680",
          "ASSOC-POSS": "#V333677",
          "LEX": "REPUTATION",
          "WNSENSE": "communication%1:03:00"
        },
        "start": 48,
        "end": 65
      },
      "V333677": {
        "id": "V333677",
        "indicator": "PRO",
        "type": "PERSON",
        "word": "MY",
        "roles": {
          "LEX": "MY",
          "PROFORM": "MY",
          "WNSENSE": "person%1:03:00"
        },
        "start": 48,
        "end": 65
      },
      "V333680": {
        "id": "V333680",
        "indicator": "F",
        "type": "OWN",
        "word": "OWN",
        "roles": {
          "FIGURE": "#V333687",
          "LEX": "OWN"
        },
        "start": 51,
        "end": 55
      },
      "root": "#V335479"
    },
    {
      "V337487": {
        "id": "V337487",
        "indicator": "SPEECHACT",
        "type": "SA_TELL",
        "word": null,
        "roles": {
          "CONTENT": "#V333508",
          "LEX": "TRIED"
        },
        "start": 0,
        "end": 23
      },
      "V333508": {
        "id": "V333508",
        "indicator": "F",
        "type": "TRY",
        "word": "TRY",
        "roles": {
          "AGENT": "#V337488",
          "FORMAL": "#V333545",
          "TENSE": "PAST",
          "LEX": "TRIED",
          "WNSENSE": "try%1:04:00::"
        },
        "start": 0,
        "end": 23
      },
      "V337488": {
        "id": "V337488",
        "indicator": "IMPRO",
        "type": "REFERENTIAL-SEM",
        "word": null,
        "roles": {
          "PROFORM": "SUBJ"
        },
        "start": 0,
        "end": 23
      },
      "V333545": {
        "id": "V333545",
        "indicator": "F",
        "type": "CAUSE-COVER",
        "word": "COVER",
        "roles": {
          "AGENT": "#V337488",
          "AFFECTED": "#V333604",
          "RESULT": "#V333584",
          "VFORM": "BASE",
          "LEX": "COVER",
          "WNSENSE": "cover%2:35:00::"
        },
        "start": 6,
        "end": 23
      },
      "V333584": {
        "id": "V333584",
        "indicator": "F",
        "type": "DIRECTION-UP",
        "word": "UP",
        "roles": {
          "FIGURE": "#V333604",
          "LEX": "UP"
        },
        "start": 15,
        "end": 18
      },
      "V333604": {
        "id": "V333604",
        "indicator": "PRO",
        "type": "REFERENTIAL-SEM",
        "word": "THAT",
        "roles": {
          "PROFORM": "THAT",
          "LEX": "THAT",
          "WNSENSE": "entity%1:03:00"
        },
        "start": 18,
        "end": 23
      },
      "root": "#V337487"
    },
    {
      "V335479": {
        "id": "V335479",
        "indicator": "SPEECHACT",
        "type": "SA_TELL",
        "word": null,
        "roles": {
          "CONTENT": "#V333633",
          "LEX": "HAPPENED"
        },
        "start": 23,
        "end": 65
      },
      "V333633": {
        "id": "V333633",
        "indicator": "F",
        "type": "HAPPEN",
        "word": "HAPPEN",
        "roles": {
          "NEUTRAL": "#V333788",
          "FORMAL": "#V333666",
          "MOD": "#V333621",
          "TENSE": "PAST",
          "LEX": "HAPPENED",
          "WNSENSE": "happen%2:41:00::"
        },
        "start": 23,
        "end": 65
      },
      "V333788": {
        "id": "V333788",
        "indicator": "THE",
        "type": "QUANTITY-ABSTR",
        "word": null,
        "roles": {
          "FIGURE": "#V333612"
        },
        "start": 23,
        "end": 26
      },
      "V333612": {
        "id": "V333612",
        "indicator": "PRO",
        "type": "REFERENTIAL-SEM",
        "word": "IT",
        "roles": {
          "PROFORM": "IT",
          "LEX": "IT",
          "WNSENSE": "entity%1:03:00"
        },
        "start": 23,
        "end": 26
      },
      "V333621": {
        "id": "V333621",
        "indicator": "F",
        "type": "MODIFIER",
        "word": "EVEN",
        "roles": {
          "FIGURE": "#V333633",
          "LEX": "EVEN",
          "WNSENSE": "even%4:02:00::"
        },
        "start": 26,
        "end": 31
      },
      "V333666": {
        "id": "V333666",
        "indicator": "F",
        "type": "RESCUE",
        "word": "SAVE",
        "roles": {
          "AGENT": "#V333788",
          "AFFECTED": "#V333687",
          "VFORM": "BASE",
          "LEX": "SAVE",
          "WNSENSE": "save%2:41:01::"
        },
        "start": 40,
        "end": 65
      },
      "V333687": {
        "id": "V333687",
        "indicator": "THE",
        "type": "INFORMATION-FUNCTION-OBJECT",
        "word": "REPUTATION",
        "roles": {
          "MOD": "#V333680",
          "ASSOC-POSS": "#V333677",
          "LEX": "REPUTATION",
          "WNSENSE": "communication%1:03:00"
        },
        "start": 48,
        "end": 65
      },
      "V333677": {
        "id": "V333677",
        "indicator": "PRO",
        "type": "PERSON",
        "word": "MY",
        "roles": {
          "LEX": "MY",
          "PROFORM": "MY",
          "WNSENSE": "person%1:03:00"
        },
        "start": 48,
        "end": 65
      },
      "V333680": {
        "id": "V333680",
        "indicator": "F",
        "type": "OWN",
        "word": "OWN",
        "roles": {
          "FIGURE": "#V333687",
          "LEX": "OWN"
        },
        "start": 51,
        "end": 55
      },
      "root": "#V335479"
    },
    {
      "V337484": {
        "id": "V337484",
        "indicator": "SPEECHACT",
        "type": "SA_TELL",
        "word": null,
        "roles": {
          "CONTENT": "#V333508",
          "LEX": "TRIED"
        },
        "start": 0,
        "end": 23
      },
      "V333508": {
        "id": "V333508",
        "indicator": "F",
        "type": "TRY",
        "word": "TRY",
        "roles": {
          "AGENT": "#V337485",
          "FORMAL": "#V333547",
          "TENSE": "PAST",
          "LEX": "TRIED",
          "WNSENSE": "try%1:04:00::"
        },
        "start": 0,
        "end": 23
      },
      "V337485": {
        "id": "V337485",
        "indicator": "IMPRO",
        "type": "REFERENTIAL-SEM",
        "word": null,
        "roles": {
          "PROFORM": "SUBJ"
        },
        "start": 0,
        "end": 23
      },
      "V333547": {
        "id": "V333547",
        "indicator": "F",
        "type": "TAKING-CARE-OF",
        "word": "COVER",
        "roles": {
          "AGENT": "#V337485",
          "AFFECTED": "#V333604",
          "RESULT": "#V333584",
          "VFORM": "BASE",
          "LEX": "COVER",
          "WNSENSE": "handle%2:41:00"
        },
        "start": 6,
        "end": 23
      },
      "V333584": {
        "id": "V333584",
        "indicator": "F",
        "type": "DIRECTION-UP",
        "word": "UP",
        "roles": {
          "FIGURE": "#V333604",
          "LEX": "UP"
        },
        "start": 15,
        "end": 18
      },
      "V333604": {
        "id": "V333604",
        "indicator": "PRO",
        "type": "REFERENTIAL-SEM",
        "word": "THAT",
        "roles": {
          "PROFORM": "THAT",
          "LEX": "THAT",
          "WNSENSE": "entity%1:03:00"
        },
        "start": 18,
        "end": 23
      },
      "root": "#V337484"
    },
    {
      "V335479": {
        "id": "V335479",
        "indicator": "SPEECHACT",
        "type": "SA_TELL",
        "word": null,
        "roles": {
          "CONTENT": "#V333633",
          "LEX": "HAPPENED"
        },
        "start": 23,
        "end": 65
      },
      "V333633": {
        "id": "V333633",
        "indicator": "F",
        "type": "HAPPEN",
        "word": "HAPPEN",
        "roles": {
          "NEUTRAL": "#V333788",
          "FORMAL": "#V333666",
          "MOD": "#V333621",
          "TENSE": "PAST",
          "LEX": "HAPPENED",
          "WNSENSE": "happen%2:41:00::"
        },
        "start": 23,
        "end": 65
      },
      "V333788": {
        "id": "V333788",
        "indicator": "THE",
        "type": "QUANTITY-ABSTR",
        "word": null,
        "roles": {
          "FIGURE": "#V333612"
        },
        "start": 23,
        "end": 26
      },
      "V333612": {
        "id": "V333612",
        "indicator": "PRO",
        "type": "REFERENTIAL-SEM",
        "word": "IT",
        "roles": {
          "PROFORM": "IT",
          "LEX": "IT",
          "WNSENSE": "entity%1:03:00"
        },
        "start": 23,
        "end": 26
      },
      "V333621": {
        "id": "V333621",
        "indicator": "F",
        "type": "MODIFIER",
        "word": "EVEN",
        "roles": {
          "FIGURE": "#V333633",
          "LEX": "EVEN",
          "WNSENSE": "even%4:02:00::"
        },
        "start": 26,
        "end": 31
      },
      "V333666": {
        "id": "V333666",
        "indicator": "F",
        "type": "RESCUE",
        "word": "SAVE",
        "roles": {
          "AGENT": "#V333788",
          "AFFECTED": "#V333687",
          "VFORM": "BASE",
          "LEX": "SAVE",
          "WNSENSE": "save%2:41:01::"
        },
        "start": 40,
        "end": 65
      },
      "V333687": {
        "id": "V333687",
        "indicator": "THE",
        "type": "INFORMATION-FUNCTION-OBJECT",
        "word": "REPUTATION",
        "roles": {
          "MOD": "#V333680",
          "ASSOC-POSS": "#V333677",
          "LEX": "REPUTATION",
          "WNSENSE": "communication%1:03:00"
        },
        "start": 48,
        "end": 65
      },
      "V333677": {
        "id": "V333677",
        "indicator": "PRO",
        "type": "PERSON",
        "word": "MY",
        "roles": {
          "LEX": "MY",
          "PROFORM": "MY",
          "WNSENSE": "person%1:03:00"
        },
        "start": 48,
        "end": 65
      },
      "V333680": {
        "id": "V333680",
        "indicator": "F",
        "type": "OWN",
        "word": "OWN",
        "roles": {
          "FIGURE": "#V333687",
          "LEX": "OWN"
        },
        "start": 51,
        "end": 55
      },
      "root": "#V335479"
    },
    {
      "V337493": {
        "id": "V337493",
        "indicator": "SPEECHACT",
        "type": "SA_TELL",
        "word": null,
        "roles": {
          "CONTENT": "#V333508",
          "LEX": "TRIED"
        },
        "start": 0,
        "end": 23
      },
      "V333508": {
        "id": "V333508",
        "indicator": "F",
        "type": "TRY",
        "word": "TRY",
        "roles": {
          "AGENT": "#V337494",
          "FORMAL": "#V333545",
          "TENSE": "PAST",
          "LEX": "TRIED",
          "WNSENSE": "try%1:04:00::"
        },
        "start": 0,
        "end": 23
      },
      "V337494": {
        "id": "V337494",
        "indicator": "IMPRO",
        "type": "REFERENTIAL-SEM",
        "word": null,
        "roles": {
          "PROFORM": "SUBJ"
        },
        "start": 0,
        "end": 23
      },
      "V333545": {
        "id": "V333545",
        "indicator": "F",
        "type": "CAUSE-COVER",
        "word": "COVER",
        "roles": {
          "AGENT": "#V337494",
          "AFFECTED": "#V333604",
          "MANNER": "#V333585",
          "VFORM": "BASE",
          "LEX": "COVER",
          "WNSENSE": "cover%2:35:00::"
        },
        "start": 6,
        "end": 23
      },
      "V333585": {
        "id": "V333585",
        "indicator": "F",
        "type": "COMPLETELY",
        "word": "UP",
        "roles": {
          "FIGURE": "#V333545",
          "LEX": "UP",
          "WNSENSE": "up%4:02:05::"
        },
        "start": 15,
        "end": 18
      },
      "V333604": {
        "id": "V333604",
        "indicator": "PRO",
        "type": "REFERENTIAL-SEM",
        "word": "THAT",
        "roles": {
          "PROFORM": "THAT",
          "LEX": "THAT",
          "WNSENSE": "entity%1:03:00"
        },
        "start": 18,
        "end": 23
      },
      "root": "#V337493"
    },
    {
      "V335579": {
        "id": "V335579",
        "indicator": "SPEECHACT",
        "type": "SA_TELL",
        "word": null,
        "roles": {
          "CONTENT": "#V333633",
          "LEX": "HAPPENED"
        },
        "start": 23,
        "end": 65
      },
      "V333633": {
        "id": "V333633",
        "indicator": "F",
        "type": "HAPPEN",
        "word": "HAPPEN",
        "roles": {
          "NEUTRAL": "#V333612",
          "FORMAL": "#V333666",
          "MOD": "#V333621",
          "TENSE": "PAST",
          "LEX": "HAPPENED",
          "WNSENSE": "happen%2:41:00::"
        },
        "start": 23,
        "end": 65
      },
      "V333612": {
        "id": "V333612",
        "indicator": "PRO",
        "type": "REFERENTIAL-SEM",
        "word": "IT",
        "roles": {
          "PROFORM": "IT",
          "LEX": "IT",
          "WNSENSE": "entity%1:03:00"
        },
        "start": 23,
        "end": 26
      },
      "V333621": {
        "id": "V333621",
        "indicator": "F",
        "type": "MODIFIER",
        "word": "EVEN",
        "roles": {
          "FIGURE": "#V333633",
          "LEX": "EVEN",
          "WNSENSE": "even%4:02:00::"
        },
        "start": 26,
        "end": 31
      },
      "V333666": {
        "id": "V333666",
        "indicator": "F",
        "type": "RESCUE",
        "word": "SAVE",
        "roles": {
          "AGENT": "#V333612",
          "AFFECTED": "#V333687",
          "VFORM": "BASE",
          "LEX": "SAVE",
          "WNSENSE": "save%2:41:01::"
        },
        "start": 40,
        "end": 65
      },
      "V333687": {
        "id": "V333687",
        "indicator": "THE",
        "type": "INFORMATION-FUNCTION-OBJECT",
        "word": "REPUTATION",
        "roles": {
          "ASSOC-POSS": "#V333677",
          "MOD": "#V333680",
          "LEX": "REPUTATION",
          "WNSENSE": "communication%1:03:00"
        },
        "start": 48,
        "end": 65
      },
      "V333677": {
        "id": "V333677",
        "indicator": "PRO",
        "type": "PERSON",
        "word": "MY",
        "roles": {
          "LEX": "MY",
          "PROFORM": "MY",
          "WNSENSE": "person%1:03:00"
        },
        "start": 48,
        "end": 65
      },
      "V333680": {
        "id": "V333680",
        "indicator": "F",
        "type": "OWN",
        "word": "OWN",
        "roles": {
          "FIGURE": "#V333687",
          "LEX": "OWN"
        },
        "start": 51,
        "end": 55
      },
      "root": "#V335579"
    },
    {
      "V337493": {
        "id": "V337493",
        "indicator": "SPEECHACT",
        "type": "SA_TELL",
        "word": null,
        "roles": {
          "CONTENT": "#V333508",
          "LEX": "TRIED"
        },
        "start": 0,
        "end": 23
      },
      "V333508": {
        "id": "V333508",
        "indicator": "F",
        "type": "TRY",
        "word": "TRY",
        "roles": {
          "AGENT": "#V337494",
          "FORMAL": "#V333545",
          "TENSE": "PAST",
          "LEX": "TRIED",
          "WNSENSE": "try%1:04:00::"
        },
        "start": 0,
        "end": 23
      },
      "V337494": {
        "id": "V337494",
        "indicator": "IMPRO",
        "type": "REFERENTIAL-SEM",
        "word": null,
        "roles": {
          "PROFORM": "SUBJ"
        },
        "start": 0,
        "end": 23
      },
      "V333545": {
        "id": "V333545",
        "indicator": "F",
        "type": "CAUSE-COVER",
        "word": "COVER",
        "roles": {
          "AGENT": "#V337494",
          "AFFECTED": "#V333604",
          "MANNER": "#V333585",
          "VFORM": "BASE",
          "LEX": "COVER",
          "WNSENSE": "cover%2:35:00::"
        },
        "start": 6,
        "end": 23
      },
      "V333585": {
        "id": "V333585",
        "indicator": "F",
        "type": "COMPLETELY",
        "word": "UP",
        "roles": {
          "FIGURE": "#V333545",
          "LEX": "UP",
          "WNSENSE": "up%4:02:05::"
        },
        "start": 15,
        "end": 18
      },
      "V333604": {
        "id": "V333604",
        "indicator": "PRO",
        "type": "REFERENTIAL-SEM",
        "word": "THAT",
        "roles": {
          "PROFORM": "THAT",
          "LEX": "THAT",
          "WNSENSE": "entity%1:03:00"
        },
        "start": 18,
        "end": 23
      },
      "root": "#V337493"
    },
    {
      "V335576": {
        "id": "V335576",
        "indicator": "SPEECHACT",
        "type": "SA_TELL",
        "word": null,
        "roles": {
          "CONTENT": "#V333633",
          "LEX": "HAPPENED"
        },
        "start": 23,
        "end": 65
      },
      "V333633": {
        "id": "V333633",
        "indicator": "F",
        "type": "HAPPEN",
        "word": "HAPPEN",
        "roles": {
          "NEUTRAL": "#V333612",
          "FORMAL": "#V333670",
          "MOD": "#V333621",
          "TENSE": "PAST",
          "LEX": "HAPPENED",
          "WNSENSE": "happen%2:41:00::"
        },
        "start": 23,
        "end": 65
      },
      "V333612": {
        "id": "V333612",
        "indicator": "PRO",
        "type": "REFERENTIAL-SEM",
        "word": "IT",
        "roles": {
          "PROFORM": "IT",
          "LEX": "IT",
          "WNSENSE": "entity%1:03:00"
        },
        "start": 23,
        "end": 26
      },
      "V333621": {
        "id": "V333621",
        "indicator": "F",
        "type": "MODIFIER",
        "word": "EVEN",
        "roles": {
          "FIGURE": "#V333633",
          "LEX": "EVEN",
          "WNSENSE": "even%4:02:00::"
        },
        "start": 26,
        "end": 31
      },
      "V333670": {
        "id": "V333670",
        "indicator": "F",
        "type": "RETAIN",
        "word": "SAVE",
        "roles": {
          "AGENT": "#V333612",
          "AFFECTED": "#V333687",
          "VFORM": "BASE",
          "LEX": "SAVE",
          "WNSENSE": "save%2:40:00::"
        },
        "start": 40,
        "end": 65
      },
      "V333687": {
        "id": "V333687",
        "indicator": "THE",
        "type": "INFORMATION-FUNCTION-OBJECT",
        "word": "REPUTATION",
        "roles": {
          "ASSOC-POSS": "#V333677",
          "MOD": "#V333680",
          "LEX": "REPUTATION",
          "WNSENSE": "communication%1:03:00"
        },
        "start": 48,
        "end": 65
      },
      "V333677": {
        "id": "V333677",
        "indicator": "PRO",
        "type": "PERSON",
        "word": "MY",
        "roles": {
          "LEX": "MY",
          "PROFORM": "MY",
          "WNSENSE": "person%1:03:00"
        },
        "start": 48,
        "end": 65
      },
      "V333680": {
        "id": "V333680",
        "indicator": "F",
        "type": "OWN",
        "word": "OWN",
        "roles": {
          "FIGURE": "#V333687",
          "LEX": "OWN"
        },
        "start": 51,
        "end": 55
      },
      "root": "#V335576"
    },
    {
      "V337490": {
        "id": "V337490",
        "indicator": "SPEECHACT",
        "type": "SA_TELL",
        "word": null,
        "roles": {
          "CONTENT": "#V333508",
          "LEX": "TRIED"
        },
        "start": 0,
        "end": 23
      },
      "V333508": {
        "id": "V333508",
        "indicator": "F",
        "type": "TRY",
        "word": "TRY",
        "roles": {
          "AGENT": "#V337491",
          "FORMAL": "#V333547",
          "TENSE": "PAST",
          "LEX": "TRIED",
          "WNSENSE": "try%1:04:00::"
        },
        "start": 0,
        "end": 23
      },
      "V337491": {
        "id": "V337491",
        "indicator": "IMPRO",
        "type": "REFERENTIAL-SEM",
        "word": null,
        "roles": {
          "PROFORM": "SUBJ"
        },
        "start": 0,
        "end": 23
      },
      "V333547": {
        "id": "V333547",
        "indicator": "F",
        "type": "TAKING-CARE-OF",
        "word": "COVER",
        "roles": {
          "AGENT": "#V337491",
          "AFFECTED": "#V333604",
          "MANNER": "#V333585",
          "VFORM": "BASE",
          "LEX": "COVER",
          "WNSENSE": "handle%2:41:00"
        },
        "start": 6,
        "end": 23
      },
      "V333585": {
        "id": "V333585",
        "indicator": "F",
        "type": "COMPLETELY",
        "word": "UP",
        "roles": {
          "FIGURE": "#V333547",
          "LEX": "UP",
          "WNSENSE": "up%4:02:05::"
        },
        "start": 15,
        "end": 18
      },
      "V333604": {
        "id": "V333604",
        "indicator": "PRO",
        "type": "REFERENTIAL-SEM",
        "word": "THAT",
        "roles": {
          "PROFORM": "THAT",
          "LEX": "THAT",
          "WNSENSE": "entity%1:03:00"
        },
        "start": 18,
        "end": 23
      },
      "root": "#V337490"
    },
    {
      "V335579": {
        "id": "V335579",
        "indicator": "SPEECHACT",
        "type": "SA_TELL",
        "word": null,
        "roles": {
          "CONTENT": "#V333633",
          "LEX": "HAPPENED"
        },
        "start": 23,
        "end": 65
      },
      "V333633": {
        "id": "V333633",
        "indicator": "F",
        "type": "HAPPEN",
        "word": "HAPPEN",
        "roles": {
          "NEUTRAL": "#V333612",
          "FORMAL": "#V333666",
          "MOD": "#V333621",
          "TENSE": "PAST",
          "LEX": "HAPPENED",
          "WNSENSE": "happen%2:41:00::"
        },
        "start": 23,
        "end": 65
      },
      "V333612": {
        "id": "V333612",
        "indicator": "PRO",
        "type": "REFERENTIAL-SEM",
        "word": "IT",
        "roles": {
          "PROFORM": "IT",
          "LEX": "IT",
          "WNSENSE": "entity%1:03:00"
        },
        "start": 23,
        "end": 26
      },
      "V333621": {
        "id": "V333621",
        "indicator": "F",
        "type": "MODIFIER",
        "word": "EVEN",
        "roles": {
          "FIGURE": "#V333633",
          "LEX": "EVEN",
          "WNSENSE": "even%4:02:00::"
        },
        "start": 26,
        "end": 31
      },
      "V333666": {
        "id": "V333666",
        "indicator": "F",
        "type": "RESCUE",
        "word": "SAVE",
        "roles": {
          "AGENT": "#V333612",
          "AFFECTED": "#V333687",
          "VFORM": "BASE",
          "LEX": "SAVE",
          "WNSENSE": "save%2:41:01::"
        },
        "start": 40,
        "end": 65
      },
      "V333687": {
        "id": "V333687",
        "indicator": "THE",
        "type": "INFORMATION-FUNCTION-OBJECT",
        "word": "REPUTATION",
        "roles": {
          "ASSOC-POSS": "#V333677",
          "MOD": "#V333680",
          "LEX": "REPUTATION",
          "WNSENSE": "communication%1:03:00"
        },
        "start": 48,
        "end": 65
      },
      "V333677": {
        "id": "V333677",
        "indicator": "PRO",
        "type": "PERSON",
        "word": "MY",
        "roles": {
          "LEX": "MY",
          "PROFORM": "MY",
          "WNSENSE": "person%1:03:00"
        },
        "start": 48,
        "end": 65
      },
      "V333680": {
        "id": "V333680",
        "indicator": "F",
        "type": "OWN",
        "word": "OWN",
        "roles": {
          "FIGURE": "#V333687",
          "LEX": "OWN"
        },
        "start": 51,
        "end": 55
      },
      "root": "#V335579"
    },
    {
      "V337490": {
        "id": "V337490",
        "indicator": "SPEECHACT",
        "type": "SA_TELL",
        "word": null,
        "roles": {
          "CONTENT": "#V333508",
          "LEX": "TRIED"
        },
        "start": 0,
        "end": 23
      },
      "V333508": {
        "id": "V333508",
        "indicator": "F",
        "type": "TRY",
        "word": "TRY",
        "roles": {
          "AGENT": "#V337491",
          "FORMAL": "#V333547",
          "TENSE": "PAST",
          "LEX": "TRIED",
          "WNSENSE": "try%1:04:00::"
        },
        "start": 0,
        "end": 23
      },
      "V337491": {
        "id": "V337491",
        "indicator": "IMPRO",
        "type": "REFERENTIAL-SEM",
        "word": null,
        "roles": {
          "PROFORM": "SUBJ"
        },
        "start": 0,
        "end": 23
      },
      "V333547": {
        "id": "V333547",
        "indicator": "F",
        "type": "TAKING-CARE-OF",
        "word": "COVER",
        "roles": {
          "AGENT": "#V337491",
          "AFFECTED": "#V333604",
          "MANNER": "#V333585",
          "VFORM": "BASE",
          "LEX": "COVER",
          "WNSENSE": "handle%2:41:00"
        },
        "start": 6,
        "end": 23
      },
      "V333585": {
        "id": "V333585",
        "indicator": "F",
        "type": "COMPLETELY",
        "word": "UP",
        "roles": {
          "FIGURE": "#V333547",
          "LEX": "UP",
          "WNSENSE": "up%4:02:05::"
        },
        "start": 15,
        "end": 18
      },
      "V333604": {
        "id": "V333604",
        "indicator": "PRO",
        "type": "REFERENTIAL-SEM",
        "word": "THAT",
        "roles": {
          "PROFORM": "THAT",
          "LEX": "THAT",
          "WNSENSE": "entity%1:03:00"
        },
        "start": 18,
        "end": 23
      },
      "root": "#V337490"
    },
    {
      "V335576": {
        "id": "V335576",
        "indicator": "SPEECHACT",
        "type": "SA_TELL",
        "word": null,
        "roles": {
          "CONTENT": "#V333633",
          "LEX": "HAPPENED"
        },
        "start": 23,
        "end": 65
      },
      "V333633": {
        "id": "V333633",
        "indicator": "F",
        "type": "HAPPEN",
        "word": "HAPPEN",
        "roles": {
          "NEUTRAL": "#V333612",
          "FORMAL": "#V333670",
          "MOD": "#V333621",
          "TENSE": "PAST",
          "LEX": "HAPPENED",
          "WNSENSE": "happen%2:41:00::"
        },
        "start": 23,
        "end": 65
      },
      "V333612": {
        "id": "V333612",
        "indicator": "PRO",
        "type": "REFERENTIAL-SEM",
        "word": "IT",
        "roles": {
          "PROFORM": "IT",
          "LEX": "IT",
          "WNSENSE": "entity%1:03:00"
        },
        "start": 23,
        "end": 26
      },
      "V333621": {
        "id": "V333621",
        "indicator": "F",
        "type": "MODIFIER",
        "word": "EVEN",
        "roles": {
          "FIGURE": "#V333633",
          "LEX": "EVEN",
          "WNSENSE": "even%4:02:00::"
        },
        "start": 26,
        "end": 31
      },
      "V333670": {
        "id": "V333670",
        "indicator": "F",
        "type": "RETAIN",
        "word": "SAVE",
        "roles": {
          "AGENT": "#V333612",
          "AFFECTED": "#V333687",
          "VFORM": "BASE",
          "LEX": "SAVE",
          "WNSENSE": "save%2:40:00::"
        },
        "start": 40,
        "end": 65
      },
      "V333687": {
        "id": "V333687",
        "indicator": "THE",
        "type": "INFORMATION-FUNCTION-OBJECT",
        "word": "REPUTATION",
        "roles": {
          "ASSOC-POSS": "#V333677",
          "MOD": "#V333680",
          "LEX": "REPUTATION",
          "WNSENSE": "communication%1:03:00"
        },
        "start": 48,
        "end": 65
      },
      "V333677": {
        "id": "V333677",
        "indicator": "PRO",
        "type": "PERSON",
        "word": "MY",
        "roles": {
          "LEX": "MY",
          "PROFORM": "MY",
          "WNSENSE": "person%1:03:00"
        },
        "start": 48,
        "end": 65
      },
      "V333680": {
        "id": "V333680",
        "indicator": "F",
        "type": "OWN",
        "word": "OWN",
        "roles": {
          "FIGURE": "#V333687",
          "LEX": "OWN"
        },
        "start": 51,
        "end": 55
      },
      "root": "#V335576"
    },
    {
      "V337487": {
        "id": "V337487",
        "indicator": "SPEECHACT",
        "type": "SA_TELL",
        "word": null,
        "roles": {
          "CONTENT": "#V333508",
          "LEX": "TRIED"
        },
        "start": 0,
        "end": 23
      },
      "V333508": {
        "id": "V333508",
        "indicator": "F",
        "type": "TRY",
        "word": "TRY",
        "roles": {
          "AGENT": "#V337488",
          "FORMAL": "#V333545",
          "TENSE": "PAST",
          "LEX": "TRIED",
          "WNSENSE": "try%1:04:00::"
        },
        "start": 0,
        "end": 23
      },
      "V337488": {
        "id": "V337488",
        "indicator": "IMPRO",
        "type": "REFERENTIAL-SEM",
        "word": null,
        "roles": {
          "PROFORM": "SUBJ"
        },
        "start": 0,
        "end": 23
      },
      "V333545": {
        "id": "V333545",
        "indicator": "F",
        "type": "CAUSE-COVER",
        "word": "COVER",
        "roles": {
          "AGENT": "#V337488",
          "AFFECTED": "#V333604",
          "RESULT": "#V333584",
          "VFORM": "BASE",
          "LEX": "COVER",
          "WNSENSE": "cover%2:35:00::"
        },
        "start": 6,
        "end": 23
      },
      "V333584": {
        "id": "V333584",
        "indicator": "F",
        "type": "DIRECTION-UP",
        "word": "UP",
        "roles": {
          "FIGURE": "#V333604",
          "LEX": "UP"
        },
        "start": 15,
        "end": 18
      },
      "V333604": {
        "id": "V333604",
        "indicator": "PRO",
        "type": "REFERENTIAL-SEM",
        "word": "THAT",
        "roles": {
          "PROFORM": "THAT",
          "LEX": "THAT",
          "WNSENSE": "entity%1:03:00"
        },
        "start": 18,
        "end": 23
      },
      "root": "#V337487"
    },
    {
      "V335579": {
        "id": "V335579",
        "indicator": "SPEECHACT",
        "type": "SA_TELL",
        "word": null,
        "roles": {
          "CONTENT": "#V333633",
          "LEX": "HAPPENED"
        },
        "start": 23,
        "end": 65
      },
      "V333633": {
        "id": "V333633",
        "indicator": "F",
        "type": "HAPPEN",
        "word": "HAPPEN",
        "roles": {
          "NEUTRAL": "#V333612",
          "FORMAL": "#V333666",
          "MOD": "#V333621",
          "TENSE": "PAST",
          "LEX": "HAPPENED",
          "WNSENSE": "happen%2:41:00::"
        },
        "start": 23,
        "end": 65
      },
      "V333612": {
        "id": "V333612",
        "indicator": "PRO",
        "type": "REFERENTIAL-SEM",
        "word": "IT",
        "roles": {
          "PROFORM": "IT",
          "LEX": "IT",
          "WNSENSE": "entity%1:03:00"
        },
        "start": 23,
        "end": 26
      },
      "V333621": {
        "id": "V333621",
        "indicator": "F",
        "type": "MODIFIER",
        "word": "EVEN",
        "roles": {
          "FIGURE": "#V333633",
          "LEX": "EVEN",
          "WNSENSE": "even%4:02:00::"
        },
        "start": 26,
        "end": 31
      },
      "V333666": {
        "id": "V333666",
        "indicator": "F",
        "type": "RESCUE",
        "word": "SAVE",
        "roles": {
          "AGENT": "#V333612",
          "AFFECTED": "#V333687",
          "VFORM": "BASE",
          "LEX": "SAVE",
          "WNSENSE": "save%2:41:01::"
        },
        "start": 40,
        "end": 65
      },
      "V333687": {
        "id": "V333687",
        "indicator": "THE",
        "type": "INFORMATION-FUNCTION-OBJECT",
        "word": "REPUTATION",
        "roles": {
          "ASSOC-POSS": "#V333677",
          "MOD": "#V333680",
          "LEX": "REPUTATION",
          "WNSENSE": "communication%1:03:00"
        },
        "start": 48,
        "end": 65
      },
      "V333677": {
        "id": "V333677",
        "indicator": "PRO",
        "type": "PERSON",
        "word": "MY",
        "roles": {
          "LEX": "MY",
          "PROFORM": "MY",
          "WNSENSE": "person%1:03:00"
        },
        "start": 48,
        "end": 65
      },
      "V333680": {
        "id": "V333680",
        "indicator": "F",
        "type": "OWN",
        "word": "OWN",
        "roles": {
          "FIGURE": "#V333687",
          "LEX": "OWN"
        },
        "start": 51,
        "end": 55
      },
      "root": "#V335579"
    },
    {
      "V337487": {
        "id": "V337487",
        "indicator": "SPEECHACT",
        "type": "SA_TELL",
        "word": null,
        "roles": {
          "CONTENT": "#V333508",
          "LEX": "TRIED"
        },
        "start": 0,
        "end": 23
      },
      "V333508": {
        "id": "V333508",
        "indicator": "F",
        "type": "TRY",
        "word": "TRY",
        "roles": {
          "AGENT": "#V337488",
          "FORMAL": "#V333545",
          "TENSE": "PAST",
          "LEX": "TRIED",
          "WNSENSE": "try%1:04:00::"
        },
        "start": 0,
        "end": 23
      },
      "V337488": {
        "id": "V337488",
        "indicator": "IMPRO",
        "type": "REFERENTIAL-SEM",
        "word": null,
        "roles": {
          "PROFORM": "SUBJ"
        },
        "start": 0,
        "end": 23
      },
      "V333545": {
        "id": "V333545",
        "indicator": "F",
        "type": "CAUSE-COVER",
        "word": "COVER",
        "roles": {
          "AGENT": "#V337488",
          "AFFECTED": "#V333604",
          "RESULT": "#V333584",
          "VFORM": "BASE",
          "LEX": "COVER",
          "WNSENSE": "cover%2:35:00::"
        },
        "start": 6,
        "end": 23
      },
      "V333584": {
        "id": "V333584",
        "indicator": "F",
        "type": "DIRECTION-UP",
        "word": "UP",
        "roles": {
          "FIGURE": "#V333604",
          "LEX": "UP"
        },
        "start": 15,
        "end": 18
      },
      "V333604": {
        "id": "V333604",
        "indicator": "PRO",
        "type": "REFERENTIAL-SEM",
        "word": "THAT",
        "roles": {
          "PROFORM": "THAT",
          "LEX": "THAT",
          "WNSENSE": "entity%1:03:00"
        },
        "start": 18,
        "end": 23
      },
      "root": "#V337487"
    },
    {
      "V335576": {
        "id": "V335576",
        "indicator": "SPEECHACT",
        "type": "SA_TELL",
        "word": null,
        "roles": {
          "CONTENT": "#V333633",
          "LEX": "HAPPENED"
        },
        "start": 23,
        "end": 65
      },
      "V333633": {
        "id": "V333633",
        "indicator": "F",
        "type": "HAPPEN",
        "word": "HAPPEN",
        "roles": {
          "NEUTRAL": "#V333612",
          "FORMAL": "#V333670",
          "MOD": "#V333621",
          "TENSE": "PAST",
          "LEX": "HAPPENED",
          "WNSENSE": "happen%2:41:00::"
        },
        "start": 23,
        "end": 65
      },
      "V333612": {
        "id": "V333612",
        "indicator": "PRO",
        "type": "REFERENTIAL-SEM",
        "word": "IT",
        "roles": {
          "PROFORM": "IT",
          "LEX": "IT",
          "WNSENSE": "entity%1:03:00"
        },
        "start": 23,
        "end": 26
      },
      "V333621": {
        "id": "V333621",
        "indicator": "F",
        "type": "MODIFIER",
        "word": "EVEN",
        "roles": {
          "FIGURE": "#V333633",
          "LEX": "EVEN",
          "WNSENSE": "even%4:02:00::"
        },
        "start": 26,
        "end": 31
      },
      "V333670": {
        "id": "V333670",
        "indicator": "F",
        "type": "RETAIN",
        "word": "SAVE",
        "roles": {
          "AGENT": "#V333612",
          "AFFECTED": "#V333687",
          "VFORM": "BASE",
          "LEX": "SAVE",
          "WNSENSE": "save%2:40:00::"
        },
        "start": 40,
        "end": 65
      },
      "V333687": {
        "id": "V333687",
        "indicator": "THE",
        "type": "INFORMATION-FUNCTION-OBJECT",
        "word": "REPUTATION",
        "roles": {
          "ASSOC-POSS": "#V333677",
          "MOD": "#V333680",
          "LEX": "REPUTATION",
          "WNSENSE": "communication%1:03:00"
        },
        "start": 48,
        "end": 65
      },
      "V333677": {
        "id": "V333677",
        "indicator": "PRO",
        "type": "PERSON",
        "word": "MY",
        "roles": {
          "LEX": "MY",
          "PROFORM": "MY",
          "WNSENSE": "person%1:03:00"
        },
        "start": 48,
        "end": 65
      },
      "V333680": {
        "id": "V333680",
        "indicator": "F",
        "type": "OWN",
        "word": "OWN",
        "roles": {
          "FIGURE": "#V333687",
          "LEX": "OWN"
        },
        "start": 51,
        "end": 55
      },
      "root": "#V335576"
    },
    {
      "V337484": {
        "id": "V337484",
        "indicator": "SPEECHACT",
        "type": "SA_TELL",
        "word": null,
        "roles": {
          "CONTENT": "#V333508",
          "LEX": "TRIED"
        },
        "start": 0,
        "end": 23
      },
      "V333508": {
        "id": "V333508",
        "indicator": "F",
        "type": "TRY",
        "word": "TRY",
        "roles": {
          "AGENT": "#V337485",
          "FORMAL": "#V333547",
          "TENSE": "PAST",
          "LEX": "TRIED",
          "WNSENSE": "try%1:04:00::"
        },
        "start": 0,
        "end": 23
      },
      "V337485": {
        "id": "V337485",
        "indicator": "IMPRO",
        "type": "REFERENTIAL-SEM",
        "word": null,
        "roles": {
          "PROFORM": "SUBJ"
        },
        "start": 0,
        "end": 23
      },
      "V333547": {
        "id": "V333547",
        "indicator": "F",
        "type": "TAKING-CARE-OF",
        "word": "COVER",
        "roles": {
          "AGENT": "#V337485",
          "AFFECTED": "#V333604",
          "RESULT": "#V333584",
          "VFORM": "BASE",
          "LEX": "COVER",
          "WNSENSE": "handle%2:41:00"
        },
        "start": 6,
        "end": 23
      },
      "V333584": {
        "id": "V333584",
        "indicator": "F",
        "type": "DIRECTION-UP",
        "word": "UP",
        "roles": {
          "FIGURE": "#V333604",
          "LEX": "UP"
        },
        "start": 15,
        "end": 18
      },
      "V333604": {
        "id": "V333604",
        "indicator": "PRO",
        "type": "REFERENTIAL-SEM",
        "word": "THAT",
        "roles": {
          "PROFORM": "THAT",
          "LEX": "THAT",
          "WNSENSE": "entity%1:03:00"
        },
        "start": 18,
        "end": 23
      },
      "root": "#V337484"
    },
    {
      "V335579": {
        "id": "V335579",
        "indicator": "SPEECHACT",
        "type": "SA_TELL",
        "word": null,
        "roles": {
          "CONTENT": "#V333633",
          "LEX": "HAPPENED"
        },
        "start": 23,
        "end": 65
      },
      "V333633": {
        "id": "V333633",
        "indicator": "F",
        "type": "HAPPEN",
        "word": "HAPPEN",
        "roles": {
          "NEUTRAL": "#V333612",
          "FORMAL": "#V333666",
          "MOD": "#V333621",
          "TENSE": "PAST",
          "LEX": "HAPPENED",
          "WNSENSE": "happen%2:41:00::"
        },
        "start": 23,
        "end": 65
      },
      "V333612": {
        "id": "V333612",
        "indicator": "PRO",
        "type": "REFERENTIAL-SEM",
        "word": "IT",
        "roles": {
          "PROFORM": "IT",
          "LEX": "IT",
          "WNSENSE": "entity%1:03:00"
        },
        "start": 23,
        "end": 26
      },
      "V333621": {
        "id": "V333621",
        "indicator": "F",
        "type": "MODIFIER",
        "word": "EVEN",
        "roles": {
          "FIGURE": "#V333633",
          "LEX": "EVEN",
          "WNSENSE": "even%4:02:00::"
        },
        "start": 26,
        "end": 31
      },
      "V333666": {
        "id": "V333666",
        "indicator": "F",
        "type": "RESCUE",
        "word": "SAVE",
        "roles": {
          "AGENT": "#V333612",
          "AFFECTED": "#V333687",
          "VFORM": "BASE",
          "LEX": "SAVE",
          "WNSENSE": "save%2:41:01::"
        },
        "start": 40,
        "end": 65
      },
      "V333687": {
        "id": "V333687",
        "indicator": "THE",
        "type": "INFORMATION-FUNCTION-OBJECT",
        "word": "REPUTATION",
        "roles": {
          "ASSOC-POSS": "#V333677",
          "MOD": "#V333680",
          "LEX": "REPUTATION",
          "WNSENSE": "communication%1:03:00"
        },
        "start": 48,
        "end": 65
      },
      "V333677": {
        "id": "V333677",
        "indicator": "PRO",
        "type": "PERSON",
        "word": "MY",
        "roles": {
          "LEX": "MY",
          "PROFORM": "MY",
          "WNSENSE": "person%1:03:00"
        },
        "start": 48,
        "end": 65
      },
      "V333680": {
        "id": "V333680",
        "indicator": "F",
        "type": "OWN",
        "word": "OWN",
        "roles": {
          "FIGURE": "#V333687",
          "LEX": "OWN"
        },
        "start": 51,
        "end": 55
      },
      "root": "#V335579"
    },
    {
      "V337484": {
        "id": "V337484",
        "indicator": "SPEECHACT",
        "type": "SA_TELL",
        "word": null,
        "roles": {
          "CONTENT": "#V333508",
          "LEX": "TRIED"
        },
        "start": 0,
        "end": 23
      },
      "V333508": {
        "id": "V333508",
        "indicator": "F",
        "type": "TRY",
        "word": "TRY",
        "roles": {
          "AGENT": "#V337485",
          "FORMAL": "#V333547",
          "TENSE": "PAST",
          "LEX": "TRIED",
          "WNSENSE": "try%1:04:00::"
        },
        "start": 0,
        "end": 23
      },
      "V337485": {
        "id": "V337485",
        "indicator": "IMPRO",
        "type": "REFERENTIAL-SEM",
        "word": null,
        "roles": {
          "PROFORM": "SUBJ"
        },
        "start": 0,
        "end": 23
      },
      "V333547": {
        "id": "V333547",
        "indicator": "F",
        "type": "TAKING-CARE-OF",
        "word": "COVER",
        "roles": {
          "AGENT": "#V337485",
          "AFFECTED": "#V333604",
          "RESULT": "#V333584",
          "VFORM": "BASE",
          "LEX": "COVER",
          "WNSENSE": "handle%2:41:00"
        },
        "start": 6,
        "end": 23
      },
      "V333584": {
        "id": "V333584",
        "indicator": "F",
        "type": "DIRECTION-UP",
        "word": "UP",
        "roles": {
          "FIGURE": "#V333604",
          "LEX": "UP"
        },
        "start": 15,
        "end": 18
      },
      "V333604": {
        "id": "V333604",
        "indicator": "PRO",
        "type": "REFERENTIAL-SEM",
        "word": "THAT",
        "roles": {
          "PROFORM": "THAT",
          "LEX": "THAT",
          "WNSENSE": "entity%1:03:00"
        },
        "start": 18,
        "end": 23
      },
      "root": "#V337484"
    },
    {
      "V335576": {
        "id": "V335576",
        "indicator": "SPEECHACT",
        "type": "SA_TELL",
        "word": null,
        "roles": {
          "CONTENT": "#V333633",
          "LEX": "HAPPENED"
        },
        "start": 23,
        "end": 65
      },
      "V333633": {
        "id": "V333633",
        "indicator": "F",
        "type": "HAPPEN",
        "word": "HAPPEN",
        "roles": {
          "NEUTRAL": "#V333612",
          "FORMAL": "#V333670",
          "MOD": "#V333621",
          "TENSE": "PAST",
          "LEX": "HAPPENED",
          "WNSENSE": "happen%2:41:00::"
        },
        "start": 23,
        "end": 65
      },
      "V333612": {
        "id": "V333612",
        "indicator": "PRO",
        "type": "REFERENTIAL-SEM",
        "word": "IT",
        "roles": {
          "PROFORM": "IT",
          "LEX": "IT",
          "WNSENSE": "entity%1:03:00"
        },
        "start": 23,
        "end": 26
      },
      "V333621": {
        "id": "V333621",
        "indicator": "F",
        "type": "MODIFIER",
        "word": "EVEN",
        "roles": {
          "FIGURE": "#V333633",
          "LEX": "EVEN",
          "WNSENSE": "even%4:02:00::"
        },
        "start": 26,
        "end": 31
      },
      "V333670": {
        "id": "V333670",
        "indicator": "F",
        "type": "RETAIN",
        "word": "SAVE",
        "roles": {
          "AGENT": "#V333612",
          "AFFECTED": "#V333687",
          "VFORM": "BASE",
          "LEX": "SAVE",
          "WNSENSE": "save%2:40:00::"
        },
        "start": 40,
        "end": 65
      },
      "V333687": {
        "id": "V333687",
        "indicator": "THE",
        "type": "INFORMATION-FUNCTION-OBJECT",
        "word": "REPUTATION",
        "roles": {
          "ASSOC-POSS": "#V333677",
          "MOD": "#V333680",
          "LEX": "REPUTATION",
          "WNSENSE": "communication%1:03:00"
        },
        "start": 48,
        "end": 65
      },
      "V333677": {
        "id": "V333677",
        "indicator": "PRO",
        "type": "PERSON",
        "word": "MY",
        "roles": {
          "LEX": "MY",
          "PROFORM": "MY",
          "WNSENSE": "person%1:03:00"
        },
        "start": 48,
        "end": 65
      },
      "V333680": {
        "id": "V333680",
        "indicator": "F",
        "type": "OWN",
        "word": "OWN",
        "roles": {
          "FIGURE": "#V333687",
          "LEX": "OWN"
        },
        "start": 51,
        "end": 55
      },
      "root": "#V335576"
    }
  ],
  "inputtags": [],
  "debug": [
    "*last-utt-id*=NIL  utt-id+55",
    "*last-utt-id*=55  utt-id+55",
    "*last-utt-id*=55  utt-id+NIL"
  ]
}
